{
  "name": "Grow-a-brain-rot",
  "tree": {
    "$className": "DataModel",

    "ReplicatedStorage": {
      "Remotes": {
        "$className": "Folder"
      }
    },
    "StarterGui": {
      "shecklesUpdater": {
        "$path": "src/client/shecklesUpdater.client.lua"
      }
    },
    "ServerScriptService": {
      "Server": {
        "$path": "src/server/Server.server.lua"
      },

      "Services": {
        "$className": "Folder",

        "DataService": {
          "$path": "src/server/services/DataService.lua",

          "ProfileStore": {
            "$path": "src/server/services/ProfileStore.lua"
          },
          "Template": {
            "$path": "src/server/services/Template.lua"
          }
        },

        "MoneyService": {
          "$path": "src/server/services/MoneyService.lua"
        },
        "PlotService": {
          "$path": "src/server/services/PlotService.lua"
        }
      }
    }
  }
}
